README.md
setup.cfg
setup.py
enisebook/__init__.py
enisebook/enisebook.py
enisebook.egg-info/PKG-INFO
enisebook.egg-info/SOURCES.txt
enisebook.egg-info/dependency_links.txt
enisebook.egg-info/top_level.txt