Metadata-Version: 1.0
Name: enisebook
Version: 0.0.1.2
Summary: A lib for making interactive books
Home-page: UNKNOWN
Author: Greg
Author-email: gregory.debono@enise.fr
License: UNKNOWN
Keywords: interactive,book
Platform: UNKNOWN
